comedy/__init__.py
comedy-0.0.1.dist-info/LICENSE
comedy-0.0.1.dist-info/METADATA
comedy-0.0.1.dist-info/WHEEL
comedy-0.0.1.dist-info/top_level.txt
comedy-0.0.1.dist-info/RECORD
